image_processing/__init__.py
image_processing/functions.py
image_processing_lib-0.22.dist-info/METADATA
image_processing_lib-0.22.dist-info/WHEEL
image_processing_lib-0.22.dist-info/top_level.txt
image_processing_lib-0.22.dist-info/RECORD
