Metadata-Version: 2.1
Name: image-processing-lib
Version: 0.22
Summary: This Python module provides utility functions for various image processing tasks, such as image conversion, display, normalization, and enhancement. It leverages the power of libraries like cv2 and numpy to handle and manipulate image data.
Home-page: https://github.com/votre_nom_utilisateur/image-processing-lib
Author: Elliot Cole
Author-email: coleelliot2001@gmail.com
License: UNKNOWN
Platform: UNKNOWN
Classifier: Programming Language :: Python :: 3
Classifier: License :: OSI Approved :: MIT License
Classifier: Operating System :: OS Independent
Requires-Dist: numpy
Requires-Dist: opencv-python
Requires-Dist: matplotlib
